setup.py
CSUMMDET.egg-info/PKG-INFO
CSUMMDET.egg-info/SOURCES.txt
CSUMMDET.egg-info/dependency_links.txt
CSUMMDET.egg-info/top_level.txt
mmdet/__init__.py
mmdet/version.py
mmdet/apis/__init__.py
mmdet/apis/env.py
mmdet/apis/inference.py
mmdet/apis/train.py
mmdet/core/__init__.py
mmdet/core/anchor/__init__.py
mmdet/core/anchor/anchor_generator.py
mmdet/core/anchor/anchor_target.py
mmdet/core/anchor/guided_anchor_target.py
mmdet/core/anchor/point_generator.py
mmdet/core/anchor/point_target.py
mmdet/core/bbox/__init__.py
mmdet/core/bbox/assign_sampling.py
mmdet/core/bbox/bbox_target.py
mmdet/core/bbox/geometry.py
mmdet/core/bbox/transforms.py
mmdet/core/bbox/assigners/__init__.py
mmdet/core/bbox/assigners/approx_max_iou_assigner.py
mmdet/core/bbox/assigners/assign_result.py
mmdet/core/bbox/assigners/base_assigner.py
mmdet/core/bbox/assigners/max_iou_assigner.py
mmdet/core/bbox/assigners/point_assigner.py
mmdet/core/bbox/samplers/__init__.py
mmdet/core/bbox/samplers/base_sampler.py
mmdet/core/bbox/samplers/combined_sampler.py
mmdet/core/bbox/samplers/instance_balanced_pos_sampler.py
mmdet/core/bbox/samplers/iou_balanced_neg_sampler.py
mmdet/core/bbox/samplers/ohem_sampler.py
mmdet/core/bbox/samplers/pseudo_sampler.py
mmdet/core/bbox/samplers/random_sampler.py
mmdet/core/bbox/samplers/sampling_result.py
mmdet/core/evaluation/__init__.py
mmdet/core/evaluation/bbox_overlaps.py
mmdet/core/evaluation/class_names.py
mmdet/core/evaluation/coco_utils.py
mmdet/core/evaluation/eval_hooks.py
mmdet/core/evaluation/mean_ap.py
mmdet/core/evaluation/recall.py
mmdet/core/fp16/__init__.py
mmdet/core/fp16/decorators.py
mmdet/core/fp16/hooks.py
mmdet/core/fp16/utils.py
mmdet/core/mask/__init__.py
mmdet/core/mask/mask_target.py
mmdet/core/mask/utils.py
mmdet/core/post_processing/__init__.py
mmdet/core/post_processing/bbox_nms.py
mmdet/core/post_processing/merge_augs.py
mmdet/core/post_processing/poly_nms.py
mmdet/core/utils/__init__.py
mmdet/core/utils/dist_utils.py
mmdet/core/utils/misc.py
mmdet/datasets/__init__.py
mmdet/datasets/builder.py
mmdet/datasets/cityscapes.py
mmdet/datasets/coco.py
